obsidian_metadata/__init__.py
obsidian_metadata/__version__.py
obsidian_metadata/_config/__init__.py
obsidian_metadata/_config/config.py
obsidian_metadata/_utils/__init__.py
obsidian_metadata/_utils/alerts.py
obsidian_metadata/_utils/console.py
obsidian_metadata/_utils/utilities.py
obsidian_metadata/cli.py
obsidian_metadata/models/__init__.py
obsidian_metadata/models/application.py
obsidian_metadata/models/enums.py
obsidian_metadata/models/exceptions.py
obsidian_metadata/models/metadata.py
obsidian_metadata/models/notes.py
obsidian_metadata/models/parsers.py
obsidian_metadata/models/questions.py
obsidian_metadata/models/vault.py
obsidian_metadata-0.12.1.dist-info/LICENSE
obsidian_metadata-0.12.1.dist-info/METADATA
obsidian_metadata-0.12.1.dist-info/WHEEL
obsidian_metadata-0.12.1.dist-info/entry_points.txt
obsidian_metadata-0.12.1.dist-info/RECORD
