Metadata-Version: 2.1
Name: obsidian-metadata
Version: 0.12.1
Summary: Make batch updates to Obsidian metadata
Home-page: https://github.com/natelandau/obsidian-metadata
License: GNU AFFERO
Keywords: obsidian
Author: Nate Landau
Author-email: github@natenate.org
Requires-Python: >=3.10,<4.0
Classifier: License :: Other/Proprietary License
Classifier: Programming Language :: Python :: 3
Classifier: Programming Language :: Python :: 3.10
Classifier: Programming Language :: Python :: 3.11
Requires-Dist: charset-normalizer (>=3.2.0,<4.0.0)
Requires-Dist: emoji (>=2.8.0,<3.0.0)
Requires-Dist: loguru (>=0.7.0,<0.8.0)
Requires-Dist: questionary (>=1.10.0,<2.0.0)
Requires-Dist: regex (>=2023.8.8,<2024.0.0)
Requires-Dist: rich (>=13.5.2,<14.0.0)
Requires-Dist: ruamel-yaml (>=0.17.32,<0.18.0)
Requires-Dist: shellingham (>=1.5.3,<2.0.0)
Requires-Dist: tomlkit (>=0.12.1,<0.13.0)
Requires-Dist: typer (>=0.9.0,<0.10.0)
Project-URL: Repository, https://github.com/natelandau/obsidian-metadata
